techlabreactor/__init__.py
techlabreactor/creep.py
techlabreactor/expansions.py
techlabreactor/gametime.py
techlabreactor/gases.py
techlabreactor/injects.py
techlabreactor/larvae.py
techlabreactor/production.py
techlabreactor/researches.py
techlabreactor/spores.py
techlabreactor/summary.py
techlabreactor/supply.py
techlabreactor/tiers.py
techlabreactor/upgrades.py
techlabreactor/util.py
techlabreactor/workers.py
techlabreactor-0.0.33.dist-info/METADATA
techlabreactor-0.0.33.dist-info/RECORD
techlabreactor-0.0.33.dist-info/WHEEL
techlabreactor-0.0.33.dist-info/top_level.txt
