Metadata-Version: 2.1
Name: techlabreactor
Version: 0.0.33
Summary: Utility for performing replay analysis of SC2 replays
Home-page: https://github.com/frugs/techlab-reactor
Author: Hugo Wainwright
Author-email: wainwrighthugo@gmail.com
License: UNKNOWN
Keywords: sc2,replay,sc2reader
Platform: UNKNOWN
Requires-Dist: sc2reader
